chaturbate_api/__init__.py
chaturbate_api/__main__.py
chaturbate_api/client.py
chaturbate_api/config.py
chaturbate_api/constants.py
chaturbate_api/event_handlers.py
chaturbate_api/exceptions.py
chaturbate_api/handlers/__init__.py
chaturbate_api/handlers/broadcast_handlers.py
chaturbate_api/handlers/chat_handlers.py
chaturbate_api/handlers/follow_handlers.py
chaturbate_api/handlers/media_handlers.py
chaturbate_api/handlers/message_handlers.py
chaturbate_api/handlers/room_handlers.py
chaturbate_api/handlers/tip_handlers.py
chaturbate_api/handlers/user_handlers.py
chaturbate_api-0.1.4.dist-info/LICENSE
chaturbate_api-0.1.4.dist-info/METADATA
chaturbate_api-0.1.4.dist-info/WHEEL
chaturbate_api-0.1.4.dist-info/RECORD
