Metadata-Version: 2.1
Name: chaturbate-api
Version: 0.1.4
Summary: Chaturbate API integration
License: MIT
Author: MountainGod2
Author-email: admin@reid.ca
Requires-Python: >=3.9,<4.0
Classifier: License :: OSI Approved :: MIT License
Classifier: Programming Language :: Python :: 3
Classifier: Programming Language :: Python :: 3.9
Classifier: Programming Language :: Python :: 3.10
Classifier: Programming Language :: Python :: 3.11
Classifier: Programming Language :: Python :: 3.12
Requires-Dist: aiohttp (>=3.9.3,<4.0.0)
Requires-Dist: aiolimiter (>=1.1.0,<2.0.0)
Requires-Dist: aioresponses (>=0.7.6,<0.8.0)
Requires-Dist: python-dotenv (>=1.0.1,<2.0.0)
